README.md
setup.cfg
setup.py
gpio_next/__init__.py
gpio_next/gpio.py
gpio_next.egg-info/PKG-INFO
gpio_next.egg-info/SOURCES.txt
gpio_next.egg-info/dependency_links.txt
gpio_next.egg-info/entry_points.txt
gpio_next.egg-info/not-zip-safe
gpio_next.egg-info/top_level.txt