Metadata-Version: 2.1
Name: gpio-next
Version: 0.0.3
Summary: libgpiod python ctypes binding
Home-page: https://github.com/voice-engine/gpio-next
Author: Yihui Xiong
Author-email: yihui.xiong@hotmail.com
License: LGPLV2
Keywords: gpio
Platform: UNKNOWN
Classifier: Development Status :: 2 - Pre-Alpha
Classifier: Intended Audience :: Developers
Classifier: License :: OSI Approved :: GNU Lesser General Public License v2 (LGPLv2)
Classifier: Natural Language :: English
Classifier: Programming Language :: Python :: 2
Classifier: Programming Language :: Python :: 2.7
Classifier: Programming Language :: Python :: 3
Classifier: Programming Language :: Python :: 3.4
Classifier: Programming Language :: Python :: 3.5
